jebus/__init__.py
jebus/add.py
jebus/subtract.py
jebus/extras/__init__.py
jebus/extras/divide.py
jebus/extras/multiply.py
jebus-0.0.1.dist-info/METADATA
jebus-0.0.1.dist-info/WHEEL
jebus-0.0.1.dist-info/top_level.txt
jebus-0.0.1.dist-info/RECORD
